jwatchsync/__init__.py
jwatchsync/jwatchsync.py
jwatchsync/event/__init__.py
jwatchsync/utils/__init__.py
jwatchsync/utils/config.py
jwatchsync-0.0.13.dist-info/METADATA
jwatchsync-0.0.13.dist-info/WHEEL
jwatchsync-0.0.13.dist-info/top_level.txt
jwatchsync-0.0.13.dist-info/RECORD
