Metadata-Version: 2.1
Name: jwatchsync
Version: 0.0.13
Summary: Libreria para escribir y consultar información en JWatch
Home-page: https://bitbucket.org/desarrolloilu/rep-ti-jwatch/src/develop/JWatchSync-PY/
Author: qquiroa
Author-email: jmata@launion.com.gt
Classifier: Programming Language :: Python :: 3
Classifier: License :: OSI Approved :: MIT License
Classifier: Operating System :: OS Independent
Requires-Python: >=3.9
Requires-Dist: requests >=2.32.4
